pelican/plugins/i18n_subsites/__init__.py
pelican/plugins/i18n_subsites/i18n_subsites.py
pelican/plugins/i18n_subsites/test_i18n_subsites.py
pelican_i18n_subsites-1.0.0.dist-info/METADATA
pelican_i18n_subsites-1.0.0.dist-info/WHEEL
pelican_i18n_subsites-1.0.0.dist-info/entry_points.txt
pelican_i18n_subsites-1.0.0.dist-info/RECORD
